litten/__init__.py
litten/utils.py
litten/layers/__init__.py
litten/layers/connectors.py
litten/layers/layers.py
litten/summary/__init__.py
litten/summary/summary.py
litten/visualize/__init__.py
litten/visualize/palettes.py
litten/visualize/visualize.py
litten-0.1.0.dist-info/LICENSE
litten-0.1.0.dist-info/METADATA
litten-0.1.0.dist-info/WHEEL
litten-0.1.0.dist-info/top_level.txt
litten-0.1.0.dist-info/RECORD
