Metadata-Version: 2.1
Name: litten
Version: 0.1.0
Summary: A python package to visualize sequentail tensorflow model archtictures
Home-page: UNKNOWN
Author: Hossam Asaad
Author-email: hossamasaad10@gmail.com
License: UNKNOWN
Keywords: python,tensorflow,keras,PIL,pillow,visualize models,visualize
Platform: UNKNOWN
Classifier: Programming Language :: Python :: 3
Classifier: License :: OSI Approved :: MIT License
Classifier: Operating System :: OS Independent
Requires-Python: >=3.6
License-File: LICENSE
Requires-Dist: Pillow (>=9.3.0)
